MANIFEST.in
README.rst
setup.py
Foundation_Sphinx_Theme.egg-info/PKG-INFO
Foundation_Sphinx_Theme.egg-info/SOURCES.txt
Foundation_Sphinx_Theme.egg-info/dependency_links.txt
Foundation_Sphinx_Theme.egg-info/requires.txt
Foundation_Sphinx_Theme.egg-info/top_level.txt
foundation_sphinx_theme/__init__.py
foundation_sphinx_theme/__init__.pyc
foundation_sphinx_theme/layout.html
foundation_sphinx_theme/theme.conf
foundation_sphinx_theme.egg-info/SOURCES.txt
foundation_sphinx_theme/static/__init__.py
foundation_sphinx_theme/static/.sass-cache/0d93976ff9f11556b314694e7a9476cfb8ac8aee/_layout.scssc
foundation_sphinx_theme/static/.sass-cache/0d93976ff9f11556b314694e7a9476cfb8ac8aee/_support.scssc
foundation_sphinx_theme/static/.sass-cache/1f687251f4be84a9c168eace54ed2ecc762c1443/_foundation-global.scssc
foundation_sphinx_theme/static/.sass-cache/364af386fb40ab5f67c4b7ae571302cd5dfce4db/_hacks.scssc
foundation_sphinx_theme/static/.sass-cache/5e9242c71e26becc8ce6caa9dd7f6fcfb2bb70e7/basic.sassc
foundation_sphinx_theme/static/.sass-cache/5e9242c71e26becc8ce6caa9dd7f6fcfb2bb70e7/cards-dark.sassc
foundation_sphinx_theme/static/.sass-cache/5e9242c71e26becc8ce6caa9dd7f6fcfb2bb70e7/cards.sassc
foundation_sphinx_theme/static/.sass-cache/6bd73e8af82090fc88833895d974195f78ecb9f5/basic.sassc
foundation_sphinx_theme/static/.sass-cache/6bd73e8af82090fc88833895d974195f78ecb9f5/cards.sassc
foundation_sphinx_theme/static/.sass-cache/6bd73e8af82090fc88833895d974195f78ecb9f5/new-cards.sassc
foundation_sphinx_theme/static/.sass-cache/793d1e7a87895ee996fa533abf984f50a9a92f0e/_grid-background.scssc
foundation_sphinx_theme/static/.sass-cache/793d1e7a87895ee996fa533abf984f50a9a92f0e/_sticky-footer.scssc
foundation_sphinx_theme/static/.sass-cache/793d1e7a87895ee996fa533abf984f50a9a92f0e/_stretching.scssc
foundation_sphinx_theme/static/.sass-cache/c88f0703a14691943a9768f6fa308feb44672b51/foundation.scssc
foundation_sphinx_theme/static/.sass-cache/cef536c96f0fa5e97a318e5438973908d5966738/_alert-boxes.scssc
foundation_sphinx_theme/static/.sass-cache/cef536c96f0fa5e97a318e5438973908d5966738/_block-grid.scssc
foundation_sphinx_theme/static/.sass-cache/cef536c96f0fa5e97a318e5438973908d5966738/_breadcrumbs.scssc
