Metadata-Version: 1.1
Name: foundation-sphinx-theme
Version: 0.0.3
Summary: UNKNOWN
Home-page: https://github.com/peterhudec/foundation-sphinx-theme
Author: Peter Hudec
Author-email: peterhudec@peterhudec.com
License: MIT
Keywords: sphinx,reStructuredText,theme,foundation
Platform: UNKNOWN
Classifier: Development Status :: 3 - Alpha
Classifier: Environment :: Web Environment
Classifier: Intended Audience :: Developers
Classifier: Intended Audience :: System Administrators
Classifier: License :: OSI Approved :: MIT License
Classifier: Operating System :: OS Independent
Classifier: Programming Language :: Python
Classifier: Topic :: Internet
Classifier: Topic :: Software Development :: Documentation
Classifier: Topic :: Text Processing :: Markup
